MedCode/__init__.py
MedCodeMap-1.4.dist-info/LICENSE
MedCodeMap-1.4.dist-info/METADATA
MedCodeMap-1.4.dist-info/WHEEL
MedCodeMap-1.4.dist-info/entry_points.txt
MedCodeMap-1.4.dist-info/top_level.txt
MedCodeMap-1.4.dist-info/RECORD
