Metadata-Version: 2.1
Name: MedCodeMap
Version: 1.4
Summary: A package for medical code mapping
Home-page: https://github.com/ycq091044/MedCodeMap
Author: Chaoqi Yang
Author-email: chaoqiy2@illinois.edu
Classifier: Programming Language :: Python :: 3
Classifier: License :: OSI Approved :: MIT License
Classifier: Operating System :: OS Independent
License-File: LICENSE
Requires-Dist: networkx
Requires-Dist: pandas
